test_app/__init__.py
test_app/test_app.py
test_app_1001-0.1.0.dist-info/METADATA
test_app_1001-0.1.0.dist-info/WHEEL
test_app_1001-0.1.0.dist-info/entry_points.txt
test_app_1001-0.1.0.dist-info/top_level.txt
test_app_1001-0.1.0.dist-info/RECORD
