Metadata-Version: 2.1
Name: test_app_1001
Version: 0.1.0
Summary: testing the distribution procedure
Author: Hamze
Author-email: hamze.najeeb@gmail.com
Classifier: Programming Language :: Python :: 3
Classifier: Operating System :: OS Independent
Requires-Python: >=3.6
